it_automation/__init__.py
it_automation/changeImage.py
it_automation/emails.py
it_automation/health_checks.py
it_automation/report_email.py
it_automation/reports.py
it_automation/run.py
it_automation/supplier_image_upload.py
it_automation_martin-1.1.1.dist-info/LICENSE
it_automation_martin-1.1.1.dist-info/METADATA
it_automation_martin-1.1.1.dist-info/WHEEL
it_automation_martin-1.1.1.dist-info/top_level.txt
it_automation_martin-1.1.1.dist-info/RECORD
