Metadata-Version: 2.1
Name: it-automation-martin
Version: 1.1.1
Summary: IT automation modules
Home-page: https://github.com/MartyDiaz/IT_Automation_Project.git
Author: Martin Diaz
Author-email: martydiaz01@gmail.com
Maintainer: Martin Diaz
Maintainer-email: martydiaz01@gmail.com
License: MIT
Platform: UNKNOWN
Classifier: License :: OSI Approved :: MIT License
Classifier: Programming Language :: Python :: 3
Classifier: Programming Language :: Python :: 3.8
License-File: LICENSE
Requires-Dist: requests
Requires-Dist: psutil
Requires-Dist: reportlab
Provides-Extra: test
Requires-Dist: pytest ; extra == 'test'
Requires-Dist: pytest-watch ; extra == 'test'
